odoo8_addon_pos_gift_ticket-8.0.0.1.0.99.dev9-nspkg.pth
odoo_addons/pos_gift_ticket/README.rst
odoo_addons/pos_gift_ticket/__init__.py
odoo_addons/pos_gift_ticket/__openerp__.py
odoo_addons/pos_gift_ticket/i18n/es.po
odoo_addons/pos_gift_ticket/i18n/fr.po
odoo_addons/pos_gift_ticket/i18n/it.po
odoo_addons/pos_gift_ticket/i18n/pos_gift_ticket.pot
odoo_addons/pos_gift_ticket/i18n/sl.po
odoo_addons/pos_gift_ticket/static/description/icon.png
odoo_addons/pos_gift_ticket/static/src/js/main.js
odoo_addons/pos_gift_ticket/static/src/xml/pos.xml
odoo_addons/pos_gift_ticket/views/pos_template.xml
odoo8_addon_pos_gift_ticket-8.0.0.1.0.99.dev9.dist-info/METADATA
odoo8_addon_pos_gift_ticket-8.0.0.1.0.99.dev9.dist-info/WHEEL
odoo8_addon_pos_gift_ticket-8.0.0.1.0.99.dev9.dist-info/namespace_packages.txt
odoo8_addon_pos_gift_ticket-8.0.0.1.0.99.dev9.dist-info/top_level.txt
odoo8_addon_pos_gift_ticket-8.0.0.1.0.99.dev9.dist-info/RECORD
