Metadata-Version: 2.1
Name: odoo8-addon-pos-gift-ticket
Version: 8.0.0.1.0.99.dev9
Summary: Gift Ticket
Home-page: http://www.factorlibre.com
Author: FactorLibre, Odoo Community Association (OCA)
Author-email: support@odoo-community.org
License: AGPL-3
Platform: UNKNOWN
Classifier: Programming Language :: Python
Classifier: Framework :: Odoo
Classifier: License :: OSI Approved :: GNU Affero General Public License v3
Requires-Python: ~=2.7
Requires-Dist: odoo (<9.0a,>=8.0a)
